{
  "parameters": {
    "subscriptionId": "89ec4d1d-dcc7-4a3f-a701-0a5d074c8505",
    "resourceGroupName": "csmrg5029",
    "api-version": "2016-09-01",
    "parameters": {
      "location": "WestUS"
    }
  },
  "responses": {
    "201": {
      "body": {
        "id": "/subscriptions/89ec4d1d-dcc7-4a3f-a701-0a5d074c8505/resourceGroups/csmrg5029",
        "name": "csmrg5029",
        "location": "westus",
        "properties": {
          "provisioningState": "Succeeded"
        }
      }
    }
  }
}