{
  "parameters": {
    "subscriptionId": "9532a63e-f2eb-4649-bb23-5ed01077ce80",
    "resourceGroupName": "csmrg2189",
    "virtualNetworkName": "azsmnet7654",
    "api-version": "2016-09-01"
  },
  "responses": {
    "200": {
      "body": {
        "name": "azsmnet7654",
        "id": "/subscriptions/9532a63e-f2eb-4649-bb23-5ed01077ce80/resourceGroups/csmrg2189/providers/Microsoft.Network/virtualNetworks/azsmnet7654",
        "etag": "W/\"96c8372b-fe3f-42a3-91e3-ded13964df63\"",
        "type": "Microsoft.Network/virtualNetworks",
        "location": "westus",
        "properties": {
          "provisioningState": "Succeeded",
          "resourceGuid": "d5707bc1-2dc0-4aba-9a2a-aecfe5d6ddb4",
          "addressSpace": {
            "addressPrefixes": [
              "10.0.0.0/16"
            ]
          },
          "dhcpOptions": {
            "dnsServers": [
              "10.1.1.1",
              "10.1.2.4"
            ]
          },
          "subnets": [
            {
              "name": "azsmnet7512",
              "id": "/subscriptions/9532a63e-f2eb-4649-bb23-5ed01077ce80/resourceGroups/csmrg2189/providers/Microsoft.Network/virtualNetworks/azsmnet7654/subnets/azsmnet7512",
              "etag": "W/\"96c8372b-fe3f-42a3-91e3-ded13964df63\"",
              "properties": {
                "provisioningState": "Succeeded",
                "addressPrefix": "10.0.0.0/24"
              }
            }
          ],
          "virtualNetworkPeerings": []
        }
      }
    }
  }
}