{
  "parameters": {
    "subscriptionId": "a083c30e-d4e5-4dc1-b310-02aaf36b316a",
    "resourceGroupName": "csmrg8131",
    "publicIpAddressName": "csmipv4publicip538",
    "api-version": "2016-09-01"
  },
  "responses": {
    "200": {
      "body": {
        "name": "csmipv4publicip538",
        "id": "/subscriptions/a083c30e-d4e5-4dc1-b310-02aaf36b316a/resourceGroups/csmrg8131/providers/Microsoft.Network/publicIPAddresses/csmipv4publicip538",
        "etag": "W/\"409b873e-2c8a-48af-bb2f-10cfcfbb77ab\"",
        "type": "Microsoft.Network/publicIPAddresses",
        "location": "eastus",
        "tags": {
          "key": "value"
        },
        "properties": {
          "provisioningState": "Succeeded",
          "resourceGuid": "8b1aea3a-31a2-4e5a-93fd-8b87bd439122",
          "publicIPAddressVersion": "IPv4",
          "publicIPAllocationMethod": "Dynamic",
          "idleTimeoutInMinutes": 4,
          "dnsSettings": {
            "domainNameLabel": "csmdnslabelpublicip1406",
            "fqdn": "csmdnslabelpublicip1406.eastus.cloudapp.azure.com"
          }
        }
      }
    }
  }
}