{
  "parameters": {
    "tenantID": "rbacclitest.onmicrosoft.com",
    "api-version": "1.6",
    "parameters": {
      "displayName": "adgroup56",
      "mailNickname": "adgroup56tester",
      "mailEnabled": false,
      "securityEnabled": true
    }
  },
  "responses": {
    "201": {
      "body": {
        "odata.metadata": "https://graph.windows.net/rbacclitest.onmicrosoft.com/$metadata#directoryObjects/Microsoft.DirectoryServices.Group/@Element",
        "odata.type": "Microsoft.DirectoryServices.Group",
        "objectType": "Group",
        "objectId": "d34e5c19-f835-4e64-bc91-d3509054c770",
        "deletionTimestamp": null,
        "description": null,
        "dirSyncEnabled": null,
        "displayName": "adgroup56",
        "lastDirSyncTime": null,
        "mail": null,
        "mailNickname": "adgroup56tester",
        "mailEnabled": false,
        "onPremisesSecurityIdentifier": null,
        "provisioningErrors": [],
        "proxyAddresses": [],
        "securityEnabled": true
      }
    }
  }
}