{
  "parameters": {
    "tenantID": "rbacclitest.onmicrosoft.com",
    "api-version": "1.6",
    "parameters": {
      "displayName": "adgroup3191",
      "mailNickname": "adgroup3191tester",
      "mailEnabled": false,
      "securityEnabled": true
    }
  },
  "responses": {
    "201": {
      "body": {
        "odata.metadata": "https://graph.windows.net/rbacclitest.onmicrosoft.com/$metadata#directoryObjects/Microsoft.DirectoryServices.Group/@Element",
        "odata.type": "Microsoft.DirectoryServices.Group",
        "objectType": "Group",
        "objectId": "72eed4e6-458b-4eca-afd3-06731bf8f927",
        "deletionTimestamp": null,
        "description": null,
        "dirSyncEnabled": null,
        "displayName": "adgroup3191",
        "lastDirSyncTime": null,
        "mail": null,
        "mailNickname": "adgroup3191tester",
        "mailEnabled": false,
        "onPremisesSecurityIdentifier": null,
        "provisioningErrors": [],
        "proxyAddresses": [],
        "securityEnabled": true
      }
    }
  }
}